splitpdf/__init__.py
splitpdf-0.1.4.dist-info/entry_points.txt
splitpdf-0.1.4.dist-info/WHEEL
splitpdf-0.1.4.dist-info/METADATA
splitpdf-0.1.4.dist-info/RECORD
