Metadata-Version: 2.1
Name: splitpdf
Version: 0.1.4
Summary: 
Author: MrTango
Author-email: md@derico.de
Requires-Python: >=3.8,<4.0
Classifier: Programming Language :: Python :: 3
Classifier: Programming Language :: Python :: 3.10
Classifier: Programming Language :: Python :: 3.8
Classifier: Programming Language :: Python :: 3.9
Requires-Dist: PyPDF2 (>=1.26.0,<2.0.0)
Requires-Dist: click (>=8.0.1,<9.0.0)
Requires-Dist: pdfreader (>=0.1.10,<0.2.0)
